CHANGES.txt
LICENSE.txt
README.txt
setup.py
js/__init__.py
js.javascript_templates.egg-info/PKG-INFO
js.javascript_templates.egg-info/SOURCES.txt
js.javascript_templates.egg-info/dependency_links.txt
js.javascript_templates.egg-info/entry_points.txt
js.javascript_templates.egg-info/namespace_packages.txt
js.javascript_templates.egg-info/not-zip-safe
js.javascript_templates.egg-info/requires.txt
js.javascript_templates.egg-info/top_level.txt
js/javascript_templates/__init__.py
js/javascript_templates/test_javascript_templates.txt
js/javascript_templates/resources/tmpl.js
js/javascript_templates/resources/tmpl.min.js