Metadata-Version: 1.0
Name: js.javascript-templates
Version: 2.1.0
Summary: Fanstatic packaging of JavaScript Templates
Home-page: UNKNOWN
Author: Andreas Kaiser
Author-email: disko@binary-punks.com
License: BSD
Platform: UNKNOWN
